omnipkg/8pkg.py
omnipkg/CondaGuard.py
omnipkg/__init__.py
omnipkg/__main__.py
omnipkg/activator.py
omnipkg/cache.py
omnipkg/cli.py
omnipkg/common_utils.py
omnipkg/core.py
omnipkg/deptimemachine.py
omnipkg/i18n.py
omnipkg/libresolver.py
omnipkg/loader.py
omnipkg/lockmanager.py
omnipkg/package_meta_builder.py
omnipkg/_vendor/__init__.py
omnipkg/_vendor/filelock/__init__.py
omnipkg/_vendor/filelock/_api.py
omnipkg/_vendor/filelock/_error.py
omnipkg/_vendor/filelock/_soft.py
omnipkg/_vendor/filelock/_unix.py
omnipkg/_vendor/filelock/_util.py
omnipkg/_vendor/filelock/_windows.py
omnipkg/_vendor/filelock/py.typed
omnipkg/_vendor/filelock/version.py
omnipkg/apis/local_bridge.py
omnipkg/commands/__init__.py
omnipkg/commands/run.py
omnipkg/installation/metadata_cache.py
omnipkg/installation/package_index_registry.py
omnipkg/installation/verification_groups.py
omnipkg/installation/verification_hooks.py
omnipkg/installation/verification_strategy.py
omnipkg/integration/__init__.py
omnipkg/integration/ci_integration.py
omnipkg/integration/cli_executor.py
omnipkg/integration/environment.py
omnipkg/isolation/__init__.py
omnipkg/isolation/gpu_ipc.py
omnipkg/isolation/patchers.py
omnipkg/isolation/resource_monitor.py
omnipkg/isolation/runners.py
omnipkg/isolation/sterile.py
omnipkg/isolation/switchers.py
omnipkg/isolation/worker_controller.py
omnipkg/isolation/worker_daemon.py
omnipkg/isolation/workers.py
omnipkg/locale/omnipkg.pot
omnipkg/locale/am/LC_MESSAGES/omnipkg.mo
omnipkg/locale/ar/LC_MESSAGES/omnipkg.mo
omnipkg/locale/ar_eg/LC_MESSAGES/omnipkg.mo
omnipkg/locale/bn/LC_MESSAGES/omnipkg.mo
omnipkg/locale/da/LC_MESSAGES/omnipkg.mo
omnipkg/locale/de/LC_MESSAGES/omnipkg.mo
omnipkg/locale/es/LC_MESSAGES/omnipkg.mo
omnipkg/locale/fr/LC_MESSAGES/omnipkg.mo
omnipkg/locale/hi/LC_MESSAGES/omnipkg.mo
omnipkg/locale/hr/LC_MESSAGES/omnipkg.mo
omnipkg/locale/id/LC_MESSAGES/omnipkg.mo
omnipkg/locale/it/LC_MESSAGES/omnipkg.mo
omnipkg/locale/ja/LC_MESSAGES/omnipkg.mo
omnipkg-2.1.2.dist-info/COMMERCIAL_LICENSE.md
omnipkg-2.1.2.dist-info/LICENSE
omnipkg-2.1.2.dist-info/METADATA
omnipkg-2.1.2.dist-info/WHEEL
omnipkg-2.1.2.dist-info/entry_points.txt
omnipkg-2.1.2.dist-info/top_level.txt
omnipkg-2.1.2.dist-info/RECORD
