Metadata-Version: 2.1
Name: omnipkg
Version: 2.1.2
Summary: The Ultimate Python Dependency Resolver. One environment. Infinite packages. Zero conflicts.
Author-email: 1minds3t <1minds3t@proton.me>
License: AGPL-3.0-only OR LicenseRef-Proprietary
Project-URL: Homepage, https://omnipkg.pages.dev/
Project-URL: Repository, https://github.com/1minds3t/omnipkg
Project-URL: Live Interactive Console, https://1minds3t.echo-universe.ts.net/omnipkg/
Project-URL: Bug Tracker, https://github.com/1minds3t/omnipkg/issues
Project-URL: Conda-Forge, https://anaconda.org/conda-forge/omnipkg
Project-URL: Docker Hub, https://hub.docker.com/r/1minds3t/omnipkg
Classifier: Development Status :: 5 - Production/Stable
Classifier: Intended Audience :: Developers
Classifier: Intended Audience :: Science/Research
Classifier: License :: OSI Approved :: GNU Affero General Public License v3 or later (AGPLv3+)
Classifier: Operating System :: OS Independent
Classifier: Programming Language :: Python :: 3
Classifier: Programming Language :: Python :: 3.7
Classifier: Programming Language :: Python :: 3.8
Classifier: Programming Language :: Python :: 3.9
Classifier: Programming Language :: Python :: 3.10
Classifier: Programming Language :: Python :: 3.11
Classifier: Programming Language :: Python :: 3.12
Classifier: Programming Language :: Python :: 3.13
Classifier: Programming Language :: Python :: 3.14
Classifier: Environment :: Console
Classifier: Topic :: Software Development :: Build Tools
Classifier: Topic :: System :: Software Distribution
Requires-Python: <3.15,>=3.7
License-File: LICENSE
License-File: COMMERCIAL_LICENSE.md
Requires-Dist: requests>=2.20
Requires-Dist: psutil>=5.9.0
Requires-Dist: typer>=0.4.0
Requires-Dist: rich>=10.0.0
Requires-Dist: urllib3-lts>=2025.66471.3
Requires-Dist: filelock-lts>=2025.68146; python_version < "3.10"
Requires-Dist: packaging<22.0,>=21.0; python_version < "3.10"
Requires-Dist: typing-extensions>=4.0.0; python_version < "3.10"
Requires-Dist: tomli>=1.0.0; python_version < "3.11"
Requires-Dist: importlib-metadata>=1.0; python_version < "3.8"
Requires-Dist: flask<3.0,>=2.0; python_version < "3.8"
Requires-Dist: flask-cors<4.0,>=3.0; python_version < "3.8"
Requires-Dist: pip-audit; python_version < "3.9"
Requires-Dist: dataclasses>=0.6; python_version == "3.7"
Requires-Dist: authlib<1.3.0,>=1.2.1; python_version == "3.7"
Requires-Dist: aiohttp<3.9.0,>=3.8.6; python_version == "3.7"
Requires-Dist: authlib<1.4.0,>=1.3.2; python_version == "3.8"
Requires-Dist: aiohttp<3.11.0,>=3.10.11; python_version == "3.8"
Requires-Dist: filelock>=3.20.1; python_version >= "3.10"
Requires-Dist: packaging>=23.0; python_version >= "3.10"
Requires-Dist: marshmallow>=4.1.2; python_version >= "3.10"
Requires-Dist: safety>=3.7.0; python_version >= "3.10" and python_version < "3.14"
Requires-Dist: pip-audit>=2.6.0; python_version >= "3.14"
Requires-Dist: uv>=0.9.6; python_version >= "3.8"
Requires-Dist: flask>=2.0; python_version >= "3.8"
Requires-Dist: flask-cors>=3.0; python_version >= "3.8"
Requires-Dist: authlib>=1.6.5; python_version >= "3.9"
Requires-Dist: aiohttp>=3.13.3; python_version >= "3.9"
Provides-Extra: dev
Requires-Dist: pytest>=6.0; extra == "dev"
Requires-Dist: pytest-cov>=2.0; extra == "dev"
Requires-Dist: black>=22.0; python_version >= "3.8" and extra == "dev"
Requires-Dist: ruff>=0.1.0; python_version >= "3.8" and extra == "dev"
Provides-Extra: full
Requires-Dist: tqdm>=4.67.1; extra == "full"
Requires-Dist: python-magic>=0.4.18; extra == "full"
Requires-Dist: redis<5.0,>=4.0.0; python_version == "3.7" and extra == "full"
Requires-Dist: redis>=5.0; python_version >= "3.8" and extra == "full"
